README.rst
setup.py
vpltest.py
vpltest.egg-info/PKG-INFO
vpltest.egg-info/SOURCES.txt
vpltest.egg-info/dependency_links.txt
vpltest.egg-info/top_level.txt