Metadata-Version: 1.1
Name: vpltest
Version: 0.5
Summary: Allows running Python tests (unittest, nose, pytest) in the context of VPL Moodle plugin (http://vpl.dis.ulpgc.es/)
Home-page: https://bitbucket.org/plas/vpltest
Author: UNKNOWN
Author-email: UNKNOWN
License: MIT
Keywords: pytest nose VPL
Platform: UNKNOWN
Classifier: Development Status :: 4 - Beta
Classifier: Intended Audience :: Developers
Classifier: Intended Audience :: Education
Classifier: License :: Freeware
Classifier: License :: OSI Approved :: MIT License
Classifier: Natural Language :: English
Classifier: Programming Language :: Python
Classifier: Programming Language :: Python :: 2
Classifier: Programming Language :: Python :: 3
Classifier: Topic :: Education
Classifier: Topic :: Software Development
Classifier: Topic :: Software Development :: Testing
